CyclicTask/ContinuousTask.py
CyclicTask/CycleTimeError.py
CyclicTask/TimedTask.py
CyclicTask/__init__.py
CyclicTask-0.1.4.dist-info/LICENSE
CyclicTask-0.1.4.dist-info/METADATA
CyclicTask-0.1.4.dist-info/WHEEL
CyclicTask-0.1.4.dist-info/top_level.txt
CyclicTask-0.1.4.dist-info/RECORD
