Metadata-Version: 2.1
Name: CyclicTask
Version: 0.1.4
Summary: Allow a task to be executed regulary
Author-email: ThunderTecke <thunder.tecke@gmail.com>
Maintainer-email: ThunderTecke <thunder.tecke@gmail.com>
License: MIT License
Project-URL: Homepage, https://github.com/ThunderTecke/CyclicTask
Project-URL: Bug Tracker, https://github.com/ThunderTecke/CyclicTask/issues
Project-URL: Change log, https://github.com/ThunderTecke/CyclicTask/blob/main/CHANGELOG.md
Keywords: Threading,Thread,Cyclic,PLC
Classifier: Development Status :: 4 - Beta
Classifier: Intended Audience :: Developers
Classifier: Intended Audience :: Education
Classifier: Intended Audience :: Science/Research
Classifier: Programming Language :: Python :: 3
Classifier: License :: OSI Approved :: MIT License
Classifier: Operating System :: OS Independent
Requires-Python: >=3.11
License-File: LICENSE
